subscriptionkore/__init__.py
subscriptionkore/config.py
subscriptionkore/factory.py
subscriptionkore/factory2.py
subscriptionkore/py.typed
subscriptionkore/adapters/__init__.py
subscriptionkore/adapters/chargebee/__init__.py
subscriptionkore/adapters/chargebee/adapter.py
subscriptionkore/adapters/lemonsqueezy/__init__.py
subscriptionkore/adapters/lemonsqueezy/adapter.py
subscriptionkore/adapters/paddle/__init__.py
subscriptionkore/adapters/paddle/adapter.py
subscriptionkore/adapters/stripe/__init__.py
subscriptionkore/adapters/stripe/adapter.py
subscriptionkore/core/__init__.py
subscriptionkore/core/exceptions.py
subscriptionkore/core/events/__init__.py
subscriptionkore/core/events/base.py
subscriptionkore/core/events/customer_events.py
subscriptionkore/core/events/payment_events.py
subscriptionkore/core/events/subscription_events.py
subscriptionkore/core/models/__init__.py
subscriptionkore/core/models/customer.py
subscriptionkore/core/models/entitlement.py
subscriptionkore/core/models/invoice.py
subscriptionkore/core/models/payment_event.py
subscriptionkore/core/models/plan.py
subscriptionkore/core/models/product.py
subscriptionkore/core/models/subscription.py
subscriptionkore/core/models/value_objects.py
subscriptionkore/core/state/__init__.py
subscriptionkore/core/state/subscription_state_machine.py
subscriptionkore/infrastructure/__init__.py
subscriptionkore/infrastructure/cache/__init__.py
subscriptionkore/infrastructure/cache/memory.py
subscriptionkore/infrastructure/cache/redis.py
subscriptionkore/infrastructure/event_bus/__init__.py
subscriptionkore/infrastructure/event_bus/memory.py
subscriptionkore/infrastructure/repositories/__init__.py
subscriptionkore/infrastructure/repositories/sqlalchemy/__init__.py
subscriptionkore/infrastructure/repositories/sqlalchemy/models.py
subscriptionkore/infrastructure/repositories/sqlalchemy/repositories.py
subscriptionkore/integrations/__init__.py
subscriptionkore/integrations/fastapi/__init__.py
subscriptionkore-0.1.0.dist-info/METADATA
subscriptionkore-0.1.0.dist-info/WHEEL
subscriptionkore-0.1.0.dist-info/RECORD
